odoo/addons/l10n_es_aeat_mod347/README.rst
odoo/addons/l10n_es_aeat_mod347/__init__.py
odoo/addons/l10n_es_aeat_mod347/__manifest__.py
odoo/addons/l10n_es_aeat_mod347/controllers/__init__.py
odoo/addons/l10n_es_aeat_mod347/controllers/main.py
odoo/addons/l10n_es_aeat_mod347/data/aeat_export_mod347_data.xml
odoo/addons/l10n_es_aeat_mod347/data/aeat_export_mod347_partner_data.xml
odoo/addons/l10n_es_aeat_mod347/data/aeat_export_mod347_real_state_data.xml
odoo/addons/l10n_es_aeat_mod347/data/l10n.es.aeat.map.tax.csv
odoo/addons/l10n_es_aeat_mod347/data/l10n.es.aeat.map.tax.line.csv
odoo/addons/l10n_es_aeat_mod347/data/l10n.es.aeat.map.tax.line.tax.csv
odoo/addons/l10n_es_aeat_mod347/data/mail_template_data.xml
odoo/addons/l10n_es_aeat_mod347/docs/347_register_design.pdf
odoo/addons/l10n_es_aeat_mod347/i18n/bg.po
odoo/addons/l10n_es_aeat_mod347/i18n/ca.po
odoo/addons/l10n_es_aeat_mod347/i18n/cs.po
odoo/addons/l10n_es_aeat_mod347/i18n/es.po
odoo/addons/l10n_es_aeat_mod347/i18n/es_CO.po
odoo/addons/l10n_es_aeat_mod347/i18n/es_CR.po
odoo/addons/l10n_es_aeat_mod347/i18n/eu.po
odoo/addons/l10n_es_aeat_mod347/i18n/fr.po
odoo/addons/l10n_es_aeat_mod347/i18n/gl.po
odoo/addons/l10n_es_aeat_mod347/i18n/hr.po
odoo/addons/l10n_es_aeat_mod347/i18n/l10n_es_aeat_mod347.pot
odoo/addons/l10n_es_aeat_mod347/i18n/nl.po
odoo/addons/l10n_es_aeat_mod347/i18n/pl.po
odoo/addons/l10n_es_aeat_mod347/i18n/pt.po
odoo/addons/l10n_es_aeat_mod347/i18n/pt_BR.po
odoo/addons/l10n_es_aeat_mod347/i18n/ru.po
odoo/addons/l10n_es_aeat_mod347/i18n/sl.po
odoo/addons/l10n_es_aeat_mod347/i18n/sv.po
odoo/addons/l10n_es_aeat_mod347/i18n/tr.po
odoo/addons/l10n_es_aeat_mod347/i18n/vi.po
odoo/addons/l10n_es_aeat_mod347/images/l10n_es_aeat_mod347.png
odoo/addons/l10n_es_aeat_mod347/migrations/18.0.1.0.0/post-migration.py
odoo/addons/l10n_es_aeat_mod347/models/__init__.py
odoo/addons/l10n_es_aeat_mod347/models/account_move.py
odoo/addons/l10n_es_aeat_mod347/models/mod347.py
odoo_addon_l10n_es_aeat_mod347-18.0.1.1.2.dist-info/METADATA
odoo_addon_l10n_es_aeat_mod347-18.0.1.1.2.dist-info/WHEEL
odoo_addon_l10n_es_aeat_mod347-18.0.1.1.2.dist-info/top_level.txt
odoo_addon_l10n_es_aeat_mod347-18.0.1.1.2.dist-info/RECORD
